shimoku_components_catalog/__init__.py
shimoku_components_catalog/html_components.py
shimoku_components_catalog-0.2.1.dist-info/AUTHORS.rst
shimoku_components_catalog-0.2.1.dist-info/LICENSE.txt
shimoku_components_catalog-0.2.1.dist-info/METADATA
shimoku_components_catalog-0.2.1.dist-info/WHEEL
shimoku_components_catalog-0.2.1.dist-info/top_level.txt
shimoku_components_catalog-0.2.1.dist-info/RECORD
