Metadata-Version: 2.1
Name: shimoku-components-catalog
Version: 0.2.1
Summary: Add a short description here!
Home-page: https://github.com/pyscaffold/pyscaffold/
Author: capitan-ariete
Author-email: sergi.ortiz.rodriguez@gmail.com
License: mit
Project-URL: Documentation, https://pyscaffold.org/
Platform: any
Classifier: Development Status :: 4 - Beta
Classifier: Programming Language :: Python
License-File: LICENSE.txt
License-File: AUTHORS.rst
Provides-Extra: testing
Requires-Dist: pytest ; extra == 'testing'
Requires-Dist: pytest-cov ; extra == 'testing'
